{
  "rev": 1,
  "scheduledFor": "2026-04-30T01:07:00+03:00",
  "runStartedAt": "2026-04-30T01:09:31+03:00",
  "timezone": "Europe/Istanbul",
  "results": [
    {
      "meta": {
        "id": "garanti",
        "rev": 1,
        "name": "Garanti BBVA",
        "sourceUrl": "https://customers.garantibbva.com.tr/digital-public/currency-convertor-public/v2/currency-convertor/currency-list-detail"
      },
      "ok": true,
      "scrapedAt": "2026-04-29T22:09:32.537Z",
      "providerUpdatedAt": "2026-04-30T00:09:28+03:00",
      "providerFingerprint": "00615ac44dbdd52c4e8cb100f9ca9187bec54f550d53688363d7fe350b85bdb4",
      "sourceUrl": "https://customers.garantibbva.com.tr/digital-public/currency-convertor-public/v2/currency-convertor/currency-list-detail",
      "data": {
        "USD/TL": {
          "buy": 44.039,
          "sell": 46.039,
          "description": "Amerikan Doları",
          "changeRatio": 0.13,
          "flagCode": "us/tr"
        },
        "TL/USD": {
          "buy": 0.021720715045939313,
          "sell": 0.022707145938826948,
          "description": "Türk Lirası",
          "changeRatio": -0.08,
          "flagCode": "tr/us"
        },
        "XPD/TL": {
          "buy": 2062.595,
          "sell": 2219.641,
          "description": "Paladyum",
          "changeRatio": 0.21,
          "flagCode": "xpd/tr"
        },
        "TL/XPD": {
          "buy": 0.0004505233053453238,
          "sell": 0.0004848261534620224,
          "description": "Türk Lirası",
          "changeRatio": -0.08,
          "flagCode": "tr/xpd"
        },
        "XPT/TL": {
          "buy": 2658.212,
          "sell": 2860.608,
          "description": "Platin",
          "changeRatio": 0.34,
          "flagCode": "xpt/tr"
        },
        "TL/XPT": {
          "buy": 0.0003495760341857395,
          "sell": 0.0003761927190156391,
          "description": "Türk Lirası",
          "changeRatio": -0.21,
          "flagCode": "tr/xpt"
        },
        "EUR/TL": {
          "buy": 51.422,
          "sell": 53.757,
          "description": "Avrupa Para Birimi",
          "changeRatio": 0.15,
          "flagCode": "eu/tr"
        },
        "TL/EUR": {
          "buy": 0.01860222854697993,
          "sell": 0.019446929329858816,
          "description": "Türk Lirası",
          "changeRatio": -0.1,
          "flagCode": "tr/eu"
        },
        "GMS/TL": {
          "buy": 98.653,
          "sell": 109.43,
          "description": "Gümüş (Gram)",
          "changeRatio": 0.17,
          "flagCode": "gms/tr"
        },
        "TL/GMS": {
          "buy": 0.009138261902586127,
          "sell": 0.01013653918279221,
          "description": "Türk Lirası",
          "changeRatio": 0.1,
          "flagCode": "tr/gms"
        },
        "ALT/TL": {
          "buy": 6497.642,
          "sell": 6953.65,
          "description": "Altın (Gram)",
          "changeRatio": 0.14,
          "flagCode": "au/tr"
        },
        "TL/ALT": {
          "buy": 0.0001438093663040274,
          "sell": 0.00015390198475077576,
          "description": "Türk Lirası",
          "changeRatio": -0.03,
          "flagCode": "tr/au"
        },
        "GBP/TL": {
          "buy": 59.357,
          "sell": 62.053,
          "description": "İngiliz Sterlini",
          "changeRatio": 0.16,
          "flagCode": "uk/tr"
        },
        "TL/GBP": {
          "buy": 0.016115256313151662,
          "sell": 0.016847212628670588,
          "description": "Türk Lirası",
          "changeRatio": -0.11,
          "flagCode": "tr/uk"
        },
        "CHF/TL": {
          "buy": 55.664,
          "sell": 58.192,
          "description": "İsviçre Frangı",
          "changeRatio": 0.18,
          "flagCode": "ch/tr"
        },
        "TL/CHF": {
          "buy": 0.01718449271377509,
          "sell": 0.01796493245185398,
          "description": "Türk Lirası",
          "changeRatio": -0.13,
          "flagCode": "tr/ch"
        },
        "AUD/TL": {
          "buy": 31.331,
          "sell": 32.754,
          "description": "Avustralya Doları",
          "changeRatio": 0.12,
          "flagCode": "aus/tr"
        },
        "TL/AUD": {
          "buy": 0.030530622214080726,
          "sell": 0.0319172704350324,
          "description": "Türk Lirası",
          "changeRatio": -0.07,
          "flagCode": "tr/aus"
        },
        "CAD/TL": {
          "buy": 32.178,
          "sell": 33.639,
          "description": "Kanada Doları",
          "changeRatio": 0.12,
          "flagCode": "ca/tr"
        },
        "TL/CAD": {
          "buy": 0.02972739974434436,
          "sell": 0.031077133445211017,
          "description": "Türk Lirası",
          "changeRatio": -0.07,
          "flagCode": "tr/ca"
        },
        "CNY/TL": {
          "buy": 6.2942,
          "sell": 6.8749,
          "description": "Çin Yuanı",
          "changeRatio": 0.16,
          "flagCode": "cn/tr"
        },
        "TL/CNY": {
          "buy": 0.1454566611877991,
          "sell": 0.1588764259159226,
          "description": "Türk Lirası",
          "changeRatio": 0.04,
          "flagCode": "tr/cn"
        },
        "DKK/TL": {
          "buy": 6.8811,
          "sell": 7.1936,
          "description": "Danimarka Kronu",
          "changeRatio": 0.15,
          "flagCode": "dk/tr"
        },
        "TL/DKK": {
          "buy": 0.13901245551601424,
          "sell": 0.14532560201130634,
          "description": "Türk Lirası",
          "changeRatio": -0.1,
          "flagCode": "tr/dk"
        },
        "JPY/TL": {
          "buy": 27.456,
          "sell": 28.703,
          "description": "Japon Yeni (100)",
          "changeRatio": 0.17,
          "flagCode": "jp/tr"
        },
        "TL/JPY": {
          "buy": 0.034839563808661114,
          "sell": 0.036421911421911424,
          "description": "Türk Lirası",
          "changeRatio": -0.12,
          "flagCode": "tr/jp"
        },
        "NOK/TL": {
          "buy": 4.717,
          "sell": 4.9312,
          "description": "Norveç Kronu",
          "changeRatio": 0.15,
          "flagCode": "no/tr"
        },
        "TL/NOK": {
          "buy": 0.2027903958468527,
          "sell": 0.211999152003392,
          "description": "Türk Lirası",
          "changeRatio": -0.1,
          "flagCode": "tr/no"
        },
        "SAR/TL": {
          "buy": 11.695,
          "sell": 12.325,
          "description": "Suudi Arabistan Riyali",
          "changeRatio": 0.13,
          "flagCode": "sa/tr"
        },
        "TL/SAR": {
          "buy": 0.08113590263691683,
          "sell": 0.08550662676357418,
          "description": "Türk Lirası",
          "changeRatio": -0.06,
          "flagCode": "tr/sa"
        },
        "SEK/TL": {
          "buy": 4.7277,
          "sell": 4.9424,
          "description": "İsveç Kronu",
          "changeRatio": 0.21,
          "flagCode": "se/tr"
        },
        "TL/SEK": {
          "buy": 0.2023308514082227,
          "sell": 0.21151934344395798,
          "description": "Türk Lirası",
          "changeRatio": -0.16,
          "flagCode": "tr/se"
        },
        "XPT/USD": {
          "buy": 58.53782,
          "sell": 62.28316,
          "description": "Platin",
          "changeRatio": 0,
          "flagCode": "xpt/us"
        },
        "USD/XPT": {
          "buy": 0.016055704302736083,
          "sell": 0.017082973024960615,
          "description": "Amerikan Doları",
          "changeRatio": 0.1,
          "flagCode": "us/xpt"
        },
        "XPD/USD": {
          "buy": 45.47893,
          "sell": 48.38874,
          "description": "Paladyum",
          "changeRatio": 0,
          "flagCode": "xpd/us"
        },
        "USD/XPD": {
          "buy": 0.020665964850500346,
          "sell": 0.021988204207970593,
          "description": "Amerikan Doları",
          "changeRatio": 0.1,
          "flagCode": "us/xpd"
        },
        "GMS/USD": {
          "buy": 2.18746,
          "sell": 2.3984,
          "description": "Gümüş (Gram)",
          "changeRatio": 0,
          "flagCode": "gms/us"
        },
        "USD/GMS": {
          "buy": 0.41694462975316876,
          "sell": 0.457151216479387,
          "description": "Amerikan Doları",
          "changeRatio": 0.21,
          "flagCode": "us/gms"
        },
        "EUR/USD": {
          "buy": 1.16633,
          "sell": 1.16867,
          "description": "Avrupa Para Birimi",
          "changeRatio": 0,
          "flagCode": "eu/us"
        },
        "USD/EUR": {
          "buy": 0.8556735434297106,
          "sell": 0.8573902754794954,
          "description": "Amerikan Doları",
          "changeRatio": 0,
          "flagCode": "us/eu"
        },
        "GBP/USD": {
          "buy": 1.3462,
          "sell": 1.3489,
          "description": "İngiliz Sterlini",
          "changeRatio": 0,
          "flagCode": "uk/us"
        },
        "USD/GBP": {
          "buy": 0.7413447994662318,
          "sell": 0.7428316743425939,
          "description": "Amerikan Doları",
          "changeRatio": 0,
          "flagCode": "us/uk"
        },
        "USD/JPY": {
          "buy": 160.28955,
          "sell": 160.61045,
          "description": "Amerikan Doları",
          "changeRatio": 0,
          "flagCode": "us/jp"
        },
        "JPY/USD": {
          "buy": 0.006226244929890926,
          "sell": 0.006238709884705523,
          "description": "Japon Yeni (100)",
          "changeRatio": 0,
          "flagCode": "jp/us"
        },
        "ALT/USD": {
          "buy": 141.55634,
          "sell": 150.61333,
          "description": "Altın (Gram)",
          "changeRatio": 0,
          "flagCode": "au/us"
        },
        "USD/ALT": {
          "buy": 0.006639518560541753,
          "sell": 0.007064325059548728,
          "description": "Amerikan Doları",
          "changeRatio": 0.1,
          "flagCode": "us/au"
        },
        "EUR/GBP": {
          "buy": 0.86466,
          "sell": 0.86812,
          "description": "Avrupa Para Birimi",
          "changeRatio": 0,
          "flagCode": "eu/uk"
        },
        "GBP/EUR": {
          "buy": 1.151914481868866,
          "sell": 1.156523951611038,
          "description": "İngiliz Sterlini",
          "changeRatio": 0,
          "flagCode": "uk/eu"
        },
        "USD/CHF": {
          "buy": 0.79071,
          "sell": 0.79229,
          "description": "Amerikan Doları",
          "changeRatio": 0,
          "flagCode": "us/ch"
        },
        "CHF/USD": {
          "buy": 1.2621641065771372,
          "sell": 1.264686168127379,
          "description": "İsviçre Frangı",
          "changeRatio": 0,
          "flagCode": "ch/us"
        },
        "EUR/CHF": {
          "buy": 0.92223,
          "sell": 0.92593,
          "description": "Avrupa Para Birimi",
          "changeRatio": 0,
          "flagCode": "eu/ch"
        },
        "CHF/EUR": {
          "buy": 1.0799952480209087,
          "sell": 1.0843282044609261,
          "description": "İsviçre Frangı",
          "changeRatio": 0,
          "flagCode": "ch/eu"
        },
        "USD/CAD": {
          "buy": 1.36708,
          "sell": 1.36982,
          "description": "Amerikan Doları",
          "changeRatio": 0,
          "flagCode": "us/ca"
        },
        "CAD/USD": {
          "buy": 0.7300229227197734,
          "sell": 0.7314860871346227,
          "description": "Kanada Doları",
          "changeRatio": 0,
          "flagCode": "ca/us"
        },
        "USD/DKK": {
          "buy": 6.3948,
          "sell": 6.4076,
          "description": "Amerikan Doları",
          "changeRatio": 0,
          "flagCode": "us/dk"
        },
        "DKK/USD": {
          "buy": 0.1560646732005743,
          "sell": 0.1563770563582911,
          "description": "Danimarka Kronu",
          "changeRatio": 0,
          "flagCode": "dk/us"
        },
        "USD/NOK": {
          "buy": 9.32821,
          "sell": 9.34689,
          "description": "Amerikan Doları",
          "changeRatio": 0,
          "flagCode": "us/no"
        },
        "NOK/USD": {
          "buy": 0.10698745786031504,
          "sell": 0.10720170322066076,
          "description": "Norveç Kronu",
          "changeRatio": 0,
          "flagCode": "no/us"
        },
        "USD/SEK": {
          "buy": 9.31253,
          "sell": 9.33117,
          "description": "Amerikan Doları",
          "changeRatio": 0,
          "flagCode": "us/se"
        },
        "SEK/USD": {
          "buy": 0.10716769708407413,
          "sell": 0.10738220440632137,
          "description": "İsveç Kronu",
          "changeRatio": 0,
          "flagCode": "se/us"
        },
        "EUR/JPY": {
          "buy": 186.95091,
          "sell": 187.70021,
          "description": "Avrupa Para Birimi",
          "changeRatio": 0,
          "flagCode": "eu/jp"
        },
        "JPY/EUR": {
          "buy": 0.005327644545522885,
          "sell": 0.005348997766312023,
          "description": "Japon Yeni (100)",
          "changeRatio": 0,
          "flagCode": "jp/eu"
        },
        "AUD/USD": {
          "buy": 0.71084,
          "sell": 0.71226,
          "description": "Avustralya Doları",
          "changeRatio": 0,
          "flagCode": "aus/us"
        },
        "USD/AUD": {
          "buy": 1.4039816920787354,
          "sell": 1.4067863372910923,
          "description": "Amerikan Doları",
          "changeRatio": 0,
          "flagCode": "us/aus"
        }
      },
      "noChange": false
    },
    {
      "meta": {
        "id": "kuveyt",
        "rev": 1,
        "name": "Kuveyt Türk",
        "sourceUrl": "https://www.kuveytturk.com.tr/ck0d84?B83A1EF44DD940F2FEC85646BDB25EA0"
      },
      "ok": true,
      "scrapedAt": "2026-04-29T22:09:33.228Z",
      "providerUpdatedAt": null,
      "providerFingerprint": "956ff6baf5c1979a3e62d84fba4c9f9008fd4e91769ed89b39ced84d1a986801",
      "sourceUrl": "https://www.kuveytturk.com.tr/ck0d84?B83A1EF44DD940F2FEC85646BDB25EA0",
      "data": {
        "USD": {
          "buy": 44.59644,
          "sell": 45.69903,
          "description": "Amerikan Doları",
          "title": "USD",
          "changeRate": 0.3912485970739174,
          "changeRateNegative": false
        },
        "EUR": {
          "buy": 52.05608,
          "sell": 53.34905,
          "description": "Euro",
          "title": "EUR",
          "changeRate": 0.2710090769903351,
          "changeRateNegative": false
        },
        "ALT (gr)": {
          "buy": 6343.61092,
          "sell": 6861.78344,
          "description": "Altın",
          "title": "ALT (gr)",
          "changeRate": 3.6383614008426552,
          "changeRateNegative": false
        },
        "GMS (gr)": {
          "buy": 100.71977,
          "sell": 108.92863,
          "description": "Gümüş",
          "title": "GMS (gr)",
          "changeRate": 3.3729049119592083,
          "changeRateNegative": false
        },
        "PLT (gr)": {
          "buy": 2676.73231,
          "sell": 2787.92794,
          "description": "Platin",
          "title": "PLT (gr)",
          "changeRate": 0.1313870530584398,
          "changeRateNegative": false
        },
        "ZCeyrek": {
          "buy": 10426.73377,
          "sell": 10855.75691,
          "description": "Çeyrek Altın (22 ayar)",
          "title": "Çeyrek",
          "changeRate": 1.0927853312424773,
          "changeRateNegative": false
        },
        "EUR/USD": {
          "buy": 1.16342,
          "sell": 1.17125,
          "description": "EUR/USD",
          "title": "EUR/USD",
          "changeRate": -0.15190655601232417,
          "changeRateNegative": true
        }
      },
      "noChange": false
    },
    {
      "meta": {
        "id": "yapi",
        "rev": 1,
        "name": "Yapı Kredi",
        "sourceUrl": "https://www.yapikredi.com.tr/_ajaxproxy/general.aspx/LoadMainCurrencies"
      },
      "ok": true,
      "scrapedAt": "2026-04-29T22:09:34.661Z",
      "providerUpdatedAt": "2026-04-30T01:08:24+03:00",
      "providerFingerprint": "9a5002e61210597056cda688508c18a4bd5fd202ff0607550406b09d501225ec",
      "sourceUrl": "https://www.yapikredi.com.tr/_ajaxproxy/general.aspx/LoadMainCurrencies",
      "data": {
        "EUR": {
          "buy": 51.19318,
          "sell": 53.6247749,
          "dailyStatus": "down",
          "change": -0.2807675,
          "previousDayBuyingPrice": 52.0403748,
          "previousDaySellingPrice": 53.0727043
        },
        "USD": {
          "buy": 43.7917023,
          "sell": 46.02319,
          "dailyStatus": "down",
          "change": -0.03944368,
          "previousDayBuyingPrice": 44.4642067,
          "previousDaySellingPrice": 45.3861275
        },
        "XAU": {
          "buy": 6426.1416,
          "sell": 6685.264,
          "dailyStatus": "down",
          "change": -0.008126041,
          "previousDayBuyingPrice": 6466.87,
          "previousDaySellingPrice": 6645.601
        }
      },
      "noChange": false
    }
  ]
}
