{
  "rev": 1,
  "scheduledFor": "2026-04-14T02:07:00+03:00",
  "runStartedAt": "2026-04-14T02:55:35+03:00",
  "timezone": "Europe/Istanbul",
  "results": [
    {
      "meta": {
        "id": "garanti",
        "rev": 1,
        "name": "Garanti BBVA",
        "sourceUrl": "https://customers.garantibbva.com.tr/digital-public/currency-convertor-public/v2/currency-convertor/currency-list-detail"
      },
      "ok": true,
      "scrapedAt": "2026-04-13T23:55:37.193Z",
      "providerUpdatedAt": "2026-04-14T00:31:58+03:00",
      "providerFingerprint": "ca51c40a4794985352cfa9c4489578906a5c38bb9704c8376b1d10b290f7810c",
      "sourceUrl": "https://customers.garantibbva.com.tr/digital-public/currency-convertor-public/v2/currency-convertor/currency-list-detail",
      "data": {
        "USD/TL": {
          "buy": 43.57,
          "sell": 45.57,
          "description": "Amerikan Doları",
          "changeRatio": 0.01,
          "flagCode": "us/tr"
        },
        "TL/USD": {
          "buy": 0.021944261575597982,
          "sell": 0.022951572182694516,
          "description": "Türk Lirası",
          "changeRatio": 0.04,
          "flagCode": "tr/us"
        },
        "XPD/TL": {
          "buy": 2204.161,
          "sell": 2372.206,
          "description": "Paladyum",
          "changeRatio": 0.17,
          "flagCode": "xpd/tr"
        },
        "TL/XPD": {
          "buy": 0.00042154855016807136,
          "sell": 0.00045368736675769147,
          "description": "Türk Lirası",
          "changeRatio": -0.03,
          "flagCode": "tr/xpd"
        },
        "XPT/TL": {
          "buy": 2897.732,
          "sell": 3118.654,
          "description": "Platin",
          "changeRatio": 0.04,
          "flagCode": "xpt/tr"
        },
        "TL/XPT": {
          "buy": 0.00032065115270882885,
          "sell": 0.0003450974762331368,
          "description": "Türk Lirası",
          "changeRatio": 0.1,
          "flagCode": "tr/xpt"
        },
        "EUR/TL": {
          "buy": 51.233,
          "sell": 53.585,
          "description": "Avrupa Para Birimi",
          "changeRatio": 0.02,
          "flagCode": "eu/tr"
        },
        "TL/EUR": {
          "buy": 0.01866193897545955,
          "sell": 0.019518669607479555,
          "description": "Türk Lirası",
          "changeRatio": 0.03,
          "flagCode": "tr/eu"
        },
        "GMS/TL": {
          "buy": 102.991,
          "sell": 114.512,
          "description": "Gümüş (Gram)",
          "changeRatio": 0.06,
          "flagCode": "gms/tr"
        },
        "TL/GMS": {
          "buy": 0.008732709235713287,
          "sell": 0.009709586274528842,
          "description": "Türk Lirası",
          "changeRatio": 0.22,
          "flagCode": "tr/gms"
        },
        "ALT/TL": {
          "buy": 6679.476,
          "sell": 7165.162,
          "description": "Altın (Gram)",
          "changeRatio": 0.04,
          "flagCode": "au/tr"
        },
        "TL/ALT": {
          "buy": 0.00013956418570857155,
          "sell": 0.00014971234270472715,
          "description": "Türk Lirası",
          "changeRatio": 0.08,
          "flagCode": "tr/au"
        },
        "GBP/TL": {
          "buy": 58.838,
          "sell": 61.539,
          "description": "İngiliz Sterlini",
          "changeRatio": 0.02,
          "flagCode": "uk/tr"
        },
        "TL/GBP": {
          "buy": 0.01624985781374413,
          "sell": 0.016995819028518985,
          "description": "Türk Lirası",
          "changeRatio": 0.03,
          "flagCode": "tr/uk"
        },
        "CHF/TL": {
          "buy": 55.595,
          "sell": 58.147,
          "description": "İsviçre Frangı",
          "changeRatio": -0.02,
          "flagCode": "ch/tr"
        },
        "TL/CHF": {
          "buy": 0.01719779180353243,
          "sell": 0.017987229067362172,
          "description": "Türk Lirası",
          "changeRatio": 0.07,
          "flagCode": "tr/ch"
        },
        "AUD/TL": {
          "buy": 30.926,
          "sell": 32.345,
          "description": "Avustralya Doları",
          "changeRatio": -0.01,
          "flagCode": "aus/tr"
        },
        "TL/AUD": {
          "buy": 0.03091667954861648,
          "sell": 0.03233525189161224,
          "description": "Türk Lirası",
          "changeRatio": 0.06,
          "flagCode": "tr/aus"
        },
        "CAD/TL": {
          "buy": 31.592,
          "sell": 33.042,
          "description": "Kanada Doları",
          "changeRatio": 0.02,
          "flagCode": "ca/tr"
        },
        "TL/CAD": {
          "buy": 0.030264511833424126,
          "sell": 0.03165358318561661,
          "description": "Türk Lirası",
          "changeRatio": 0.03,
          "flagCode": "tr/ca"
        },
        "CNY/TL": {
          "buy": 6.2522,
          "sell": 6.8334,
          "description": "Çin Yuanı",
          "changeRatio": 0.01,
          "flagCode": "cn/tr"
        },
        "TL/CNY": {
          "buy": 0.1463400357069687,
          "sell": 0.15994369981766418,
          "description": "Türk Lirası",
          "changeRatio": 0.19,
          "flagCode": "tr/cn"
        },
        "DKK/TL": {
          "buy": 6.8563,
          "sell": 7.171,
          "description": "Danimarka Kronu",
          "changeRatio": 0.02,
          "flagCode": "dk/tr"
        },
        "TL/DKK": {
          "buy": 0.13945056477478734,
          "sell": 0.14585126088415035,
          "description": "Türk Lirası",
          "changeRatio": 0.03,
          "flagCode": "tr/dk"
        },
        "JPY/TL": {
          "buy": 27.34,
          "sell": 28.595,
          "description": "Japon Yeni (100)",
          "changeRatio": -0.03,
          "flagCode": "jp/tr"
        },
        "TL/JPY": {
          "buy": 0.03497114880223816,
          "sell": 0.036576444769568395,
          "description": "Türk Lirası",
          "changeRatio": 0.08,
          "flagCode": "tr/jp"
        },
        "NOK/TL": {
          "buy": 4.6116,
          "sell": 4.8233,
          "description": "Norveç Kronu",
          "changeRatio": -0.02,
          "flagCode": "no/tr"
        },
        "TL/NOK": {
          "buy": 0.20732693384197542,
          "sell": 0.2168444791395611,
          "description": "Türk Lirası",
          "changeRatio": 0.07,
          "flagCode": "tr/no"
        },
        "SAR/TL": {
          "buy": 11.563,
          "sell": 12.191,
          "description": "Suudi Arabistan Riyali",
          "changeRatio": 0,
          "flagCode": "sa/tr"
        },
        "TL/SAR": {
          "buy": 0.08202772537117545,
          "sell": 0.08648274669203493,
          "description": "Türk Lirası",
          "changeRatio": 0.07,
          "flagCode": "tr/sa"
        },
        "SEK/TL": {
          "buy": 4.7409,
          "sell": 4.9585,
          "description": "İsveç Kronu",
          "changeRatio": -0.09,
          "flagCode": "se/tr"
        },
        "TL/SEK": {
          "buy": 0.20167389331451044,
          "sell": 0.2109304140564028,
          "description": "Türk Lirası",
          "changeRatio": 0.14,
          "flagCode": "tr/se"
        },
        "XPT/USD": {
          "buy": 64.59674,
          "sell": 68.72974,
          "description": "Platin",
          "changeRatio": 0,
          "flagCode": "xpt/us"
        },
        "USD/XPT": {
          "buy": 0.014549742222217048,
          "sell": 0.015480657383019639,
          "description": "Amerikan Doları",
          "changeRatio": 0.1,
          "flagCode": "us/xpt"
        },
        "XPD/USD": {
          "buy": 49.07191,
          "sell": 52.2116,
          "description": "Paladyum",
          "changeRatio": 0,
          "flagCode": "xpd/us"
        },
        "USD/XPD": {
          "buy": 0.019152831937730312,
          "sell": 0.020378257133256073,
          "description": "Amerikan Doları",
          "changeRatio": 0.1,
          "flagCode": "us/xpd"
        },
        "GMS/USD": {
          "buy": 2.3177,
          "sell": 2.5412,
          "description": "Gümüş (Gram)",
          "changeRatio": 0,
          "flagCode": "gms/us"
        },
        "USD/GMS": {
          "buy": 0.3935148748622698,
          "sell": 0.43146222548215907,
          "description": "Amerikan Doları",
          "changeRatio": 0.21,
          "flagCode": "us/gms"
        },
        "EUR/USD": {
          "buy": 1.17452,
          "sell": 1.17688,
          "description": "Avrupa Para Birimi",
          "changeRatio": 0,
          "flagCode": "eu/us"
        },
        "USD/EUR": {
          "buy": 0.8497043029025899,
          "sell": 0.8514116404999489,
          "description": "Amerikan Doları",
          "changeRatio": 0,
          "flagCode": "us/eu"
        },
        "GBP/USD": {
          "buy": 1.3489,
          "sell": 1.3516,
          "description": "İngiliz Sterlini",
          "changeRatio": 0,
          "flagCode": "uk/us"
        },
        "USD/GBP": {
          "buy": 0.7398638650488311,
          "sell": 0.7413447994662318,
          "description": "Amerikan Doları",
          "changeRatio": 0,
          "flagCode": "us/uk"
        },
        "USD/JPY": {
          "buy": 159.1407,
          "sell": 159.4593,
          "description": "Amerikan Doları",
          "changeRatio": 0,
          "flagCode": "us/jp"
        },
        "JPY/USD": {
          "buy": 0.006271192711870677,
          "sell": 0.006283747652234783,
          "description": "Japon Yeni (100)",
          "changeRatio": 0,
          "flagCode": "jp/us"
        },
        "ALT/USD": {
          "buy": 147.67987,
          "sell": 157.12865,
          "description": "Altın (Gram)",
          "changeRatio": 0,
          "flagCode": "au/us"
        },
        "USD/ALT": {
          "buy": 0.006364211746234694,
          "sell": 0.006771403577210625,
          "description": "Amerikan Doları",
          "changeRatio": 0.1,
          "flagCode": "us/au"
        },
        "EUR/GBP": {
          "buy": 0.86899,
          "sell": 0.87247,
          "description": "Avrupa Para Birimi",
          "changeRatio": 0,
          "flagCode": "eu/uk"
        },
        "GBP/EUR": {
          "buy": 1.1461712150561052,
          "sell": 1.1507612285526876,
          "description": "İngiliz Sterlini",
          "changeRatio": 0,
          "flagCode": "uk/eu"
        },
        "USD/CHF": {
          "buy": 0.78272,
          "sell": 0.78428,
          "description": "Amerikan Doları",
          "changeRatio": 0,
          "flagCode": "us/ch"
        },
        "CHF/USD": {
          "buy": 1.2750548273575764,
          "sell": 1.277596075224857,
          "description": "İsviçre Frangı",
          "changeRatio": 0,
          "flagCode": "ch/us"
        },
        "EUR/CHF": {
          "buy": 0.91932,
          "sell": 0.923,
          "description": "Avrupa Para Birimi",
          "changeRatio": 0,
          "flagCode": "eu/ch"
        },
        "CHF/EUR": {
          "buy": 1.0834236186348862,
          "sell": 1.0877605186442152,
          "description": "İsviçre Frangı",
          "changeRatio": 0,
          "flagCode": "ch/eu"
        },
        "USD/CAD": {
          "buy": 1.37787,
          "sell": 1.38063,
          "description": "Amerikan Doları",
          "changeRatio": 0,
          "flagCode": "us/ca"
        },
        "CAD/USD": {
          "buy": 0.7243070192593236,
          "sell": 0.7257578726585237,
          "description": "Kanada Doları",
          "changeRatio": 0,
          "flagCode": "ca/us"
        },
        "USD/DKK": {
          "buy": 6.34914,
          "sell": 6.36186,
          "description": "Amerikan Doları",
          "changeRatio": 0,
          "flagCode": "us/dk"
        },
        "DKK/USD": {
          "buy": 0.15718673469708544,
          "sell": 0.15750164589219956,
          "description": "Danimarka Kronu",
          "changeRatio": 0,
          "flagCode": "dk/us"
        },
        "USD/NOK": {
          "buy": 9.43541,
          "sell": 9.4543,
          "description": "Amerikan Doları",
          "changeRatio": 0,
          "flagCode": "us/no"
        },
        "NOK/USD": {
          "buy": 0.10577197677247391,
          "sell": 0.10598373573591398,
          "description": "Norveç Kronu",
          "changeRatio": 0,
          "flagCode": "no/us"
        },
        "USD/SEK": {
          "buy": 9.17252,
          "sell": 9.19088,
          "description": "Amerikan Doları",
          "changeRatio": 0,
          "flagCode": "us/se"
        },
        "SEK/USD": {
          "buy": 0.10880350956600456,
          "sell": 0.10902129403915173,
          "description": "İsveç Kronu",
          "changeRatio": 0,
          "flagCode": "se/us"
        },
        "EUR/JPY": {
          "buy": 186.91462,
          "sell": 187.66378,
          "description": "Avrupa Para Birimi",
          "changeRatio": 0,
          "flagCode": "eu/jp"
        },
        "JPY/EUR": {
          "buy": 0.005328678767954051,
          "sell": 0.00535003628929615,
          "description": "Japon Yeni (100)",
          "changeRatio": 0,
          "flagCode": "jp/eu"
        },
        "AUD/USD": {
          "buy": 0.70919,
          "sell": 0.71061,
          "description": "Avustralya Doları",
          "changeRatio": 0,
          "flagCode": "aus/us"
        },
        "USD/AUD": {
          "buy": 1.4072416656112354,
          "sell": 1.4100593634992034,
          "description": "Amerikan Doları",
          "changeRatio": 0,
          "flagCode": "us/aus"
        }
      },
      "noChange": true
    },
    {
      "meta": {
        "id": "kuveyt",
        "rev": 1,
        "name": "Kuveyt Türk",
        "sourceUrl": "https://www.kuveytturk.com.tr/ck0d84?B83A1EF44DD940F2FEC85646BDB25EA0"
      },
      "ok": true,
      "scrapedAt": "2026-04-13T23:55:37.921Z",
      "providerUpdatedAt": null,
      "providerFingerprint": "7419b5cb08508278d77eb603d779bff9064a4093af8c3a9162b4cf8ad288141b",
      "sourceUrl": "https://www.kuveytturk.com.tr/ck0d84?B83A1EF44DD940F2FEC85646BDB25EA0",
      "data": {
        "USD": {
          "buy": 44.10173,
          "sell": 45.24233,
          "description": "Amerikan Doları",
          "title": "USD",
          "changeRate": 0.1652065158937657,
          "changeRateNegative": false
        },
        "EUR": {
          "buy": 51.88525,
          "sell": 53.23212,
          "description": "Euro",
          "title": "EUR",
          "changeRate": 0.6742999320291144,
          "changeRateNegative": false
        },
        "ALT (gr)": {
          "buy": 6666.14868,
          "sell": 6873.38326,
          "description": "Altın",
          "title": "ALT (gr)",
          "changeRate": 0.52517151584262,
          "changeRateNegative": false
        },
        "GMS (gr)": {
          "buy": 106.60248,
          "sell": 109.93906,
          "description": "Gümüş",
          "title": "GMS (gr)",
          "changeRate": 2.075500305607042,
          "changeRateNegative": false
        },
        "PLT (gr)": {
          "buy": 2930.29038,
          "sell": 3043.88453,
          "description": "Platin",
          "title": "PLT (gr)",
          "changeRate": 2.505609970378257,
          "changeRateNegative": false
        },
        "ZCeyrek": {
          "buy": 10794.32188,
          "sell": 11249.20771,
          "description": "Çeyrek Altın (22 ayar)",
          "title": "Çeyrek",
          "changeRate": 0.8549239358345835,
          "changeRateNegative": false
        },
        "EUR/USD": {
          "buy": 1.17261,
          "sell": 1.18048,
          "description": "EUR/USD",
          "title": "EUR/USD",
          "changeRate": 0.47383212804606367,
          "changeRateNegative": false
        }
      },
      "noChange": false
    },
    {
      "meta": {
        "id": "yapi",
        "rev": 1,
        "name": "Yapı Kredi",
        "sourceUrl": "https://www.yapikredi.com.tr/_ajaxproxy/general.aspx/LoadMainCurrencies"
      },
      "ok": true,
      "scrapedAt": "2026-04-13T23:55:39.089Z",
      "providerUpdatedAt": "2026-04-14T02:52:30+03:00",
      "providerFingerprint": "e3e201932acd0c943219197d47fff7af8b1e16c6a17f6eb4fa7b1a47097c2a79",
      "sourceUrl": "https://www.yapikredi.com.tr/_ajaxproxy/general.aspx/LoadMainCurrencies",
      "data": {
        "EUR": {
          "buy": 51.2466,
          "sell": 53.7318039,
          "dailyStatus": "up",
          "change": 0.451339871,
          "previousDayBuyingPrice": 51.73629,
          "previousDaySellingPrice": 52.7704353
        },
        "USD": {
          "buy": 43.4786034,
          "sell": 45.75396,
          "dailyStatus": "down",
          "change": -0.02167862,
          "previousDayBuyingPrice": 44.16454,
          "previousDaySellingPrice": 45.08737
        },
        "XAU": {
          "buy": 6676.10352,
          "sell": 6943.77148,
          "dailyStatus": "up",
          "change": 0.788476944,
          "previousDayBuyingPrice": 6666.289,
          "previousDaySellingPrice": 6847.03662
        }
      },
      "noChange": false
    }
  ]
}
