{
  "rev": 1,
  "scheduledFor": "2026-04-17T23:07:00+03:00",
  "runStartedAt": "2026-04-17T23:59:52+03:00",
  "timezone": "Europe/Istanbul",
  "results": [
    {
      "meta": {
        "id": "garanti",
        "rev": 1,
        "name": "Garanti BBVA",
        "sourceUrl": "https://customers.garantibbva.com.tr/digital-public/currency-convertor-public/v2/currency-convertor/currency-list-detail"
      },
      "ok": true,
      "scrapedAt": "2026-04-17T20:59:54.966Z",
      "providerUpdatedAt": "2026-04-17T21:52:42+03:00",
      "providerFingerprint": "c9322d04f4c40909432a5b1f4d897b27e0e4259b920395c9cf4a61a4806acd33",
      "sourceUrl": "https://customers.garantibbva.com.tr/digital-public/currency-convertor-public/v2/currency-convertor/currency-list-detail",
      "data": {
        "USD/TL": {
          "buy": 43.629,
          "sell": 45.629,
          "description": "Amerikan Doları",
          "changeRatio": 0.02,
          "flagCode": "us/tr"
        },
        "TL/USD": {
          "buy": 0.02191588682636043,
          "sell": 0.022920534506864702,
          "description": "Türk Lirası",
          "changeRatio": 0.03,
          "flagCode": "tr/us"
        },
        "XPD/TL": {
          "buy": 2201.398,
          "sell": 2369.204,
          "description": "Paladyum",
          "changeRatio": 0.63,
          "flagCode": "xpd/tr"
        },
        "TL/XPD": {
          "buy": 0.0004220826910641717,
          "sell": 0.000454256795000268,
          "description": "Türk Lirası",
          "changeRatio": -0.49,
          "flagCode": "tr/xpd"
        },
        "XPT/TL": {
          "buy": 2968.493,
          "sell": 3194.773,
          "description": "Platin",
          "changeRatio": 0.92,
          "flagCode": "xpt/tr"
        },
        "TL/XPT": {
          "buy": 0.00031301128436981283,
          "sell": 0.0003368712676768987,
          "description": "Türk Lirası",
          "changeRatio": -0.78,
          "flagCode": "tr/xpt"
        },
        "EUR/TL": {
          "buy": 51.373,
          "sell": 53.728,
          "description": "Avrupa Para Birimi",
          "changeRatio": -0.06,
          "flagCode": "eu/tr"
        },
        "TL/EUR": {
          "buy": 0.018612269207861822,
          "sell": 0.01946547797481167,
          "description": "Türk Lirası",
          "changeRatio": 0.11,
          "flagCode": "tr/eu"
        },
        "GMS/TL": {
          "buy": 111.631,
          "sell": 123.836,
          "description": "Gümüş (Gram)",
          "changeRatio": 3.63,
          "flagCode": "gms/tr"
        },
        "TL/GMS": {
          "buy": 0.008075196227268322,
          "sell": 0.008958085119724808,
          "description": "Türk Lirası",
          "changeRatio": -3.24,
          "flagCode": "tr/gms"
        },
        "ALT/TL": {
          "buy": 6880.998,
          "sell": 7364.504,
          "description": "Altın (Gram)",
          "changeRatio": 1.35,
          "flagCode": "au/tr"
        },
        "TL/ALT": {
          "buy": 0.00013578646980163227,
          "sell": 0.00014532775623536006,
          "description": "Türk Lirası",
          "changeRatio": -1.22,
          "flagCode": "tr/au"
        },
        "GBP/TL": {
          "buy": 59.047,
          "sell": 61.754,
          "description": "İngiliz Sterlini",
          "changeRatio": 0.03,
          "flagCode": "uk/tr"
        },
        "TL/GBP": {
          "buy": 0.016193283026200732,
          "sell": 0.01693566142225685,
          "description": "Türk Lirası",
          "changeRatio": 0.02,
          "flagCode": "tr/uk"
        },
        "CHF/TL": {
          "buy": 55.859,
          "sell": 58.42,
          "description": "İsviçre Frangı",
          "changeRatio": 0.27,
          "flagCode": "ch/tr"
        },
        "TL/CHF": {
          "buy": 0.017117425539198903,
          "sell": 0.017902218084820707,
          "description": "Türk Lirası",
          "changeRatio": -0.22,
          "flagCode": "tr/ch"
        },
        "AUD/TL": {
          "buy": 31.288,
          "sell": 32.723,
          "description": "Avustralya Doları",
          "changeRatio": 0.15,
          "flagCode": "aus/tr"
        },
        "TL/AUD": {
          "buy": 0.030559545273966326,
          "sell": 0.03196113525952442,
          "description": "Türk Lirası",
          "changeRatio": -0.1,
          "flagCode": "tr/aus"
        },
        "CAD/TL": {
          "buy": 31.887,
          "sell": 33.348,
          "description": "Kanada Doları",
          "changeRatio": 0.13,
          "flagCode": "ca/tr"
        },
        "TL/CAD": {
          "buy": 0.029986805805445604,
          "sell": 0.0313607426223853,
          "description": "Türk Lirası",
          "changeRatio": -0.08,
          "flagCode": "tr/ca"
        },
        "CNY/TL": {
          "buy": 6.2629,
          "sell": 6.8448,
          "description": "Çin Yuanı",
          "changeRatio": 0.1,
          "flagCode": "cn/tr"
        },
        "TL/CNY": {
          "buy": 0.146096306685367,
          "sell": 0.15967044021140367,
          "description": "Türk Lirası",
          "changeRatio": 0.1,
          "flagCode": "tr/cn"
        },
        "DKK/TL": {
          "buy": 6.8746,
          "sell": 7.1897,
          "description": "Danimarka Kronu",
          "changeRatio": -0.06,
          "flagCode": "dk/tr"
        },
        "TL/DKK": {
          "buy": 0.1390878618023005,
          "sell": 0.14546300875687312,
          "description": "Türk Lirası",
          "changeRatio": 0.11,
          "flagCode": "tr/dk"
        },
        "JPY/TL": {
          "buy": 27.535,
          "sell": 28.797,
          "description": "Japon Yeni (100)",
          "changeRatio": 0.44,
          "flagCode": "jp/tr"
        },
        "TL/JPY": {
          "buy": 0.03472583949716984,
          "sell": 0.03631741420010895,
          "description": "Türk Lirası",
          "changeRatio": -0.39,
          "flagCode": "tr/jp"
        },
        "NOK/TL": {
          "buy": 4.651,
          "sell": 4.8642,
          "description": "Norveç Kronu",
          "changeRatio": -0.18,
          "flagCode": "no/tr"
        },
        "TL/NOK": {
          "buy": 0.20558365198799392,
          "sell": 0.21500752526338424,
          "description": "Türk Lirası",
          "changeRatio": 0.23,
          "flagCode": "tr/no"
        },
        "SAR/TL": {
          "buy": 11.584,
          "sell": 12.213,
          "description": "Suudi Arabistan Riyali",
          "changeRatio": 0.03,
          "flagCode": "sa/tr"
        },
        "TL/SAR": {
          "buy": 0.08187996397281586,
          "sell": 0.08632596685082873,
          "description": "Türk Lirası",
          "changeRatio": 0.04,
          "flagCode": "tr/sa"
        },
        "SEK/TL": {
          "buy": 4.7643,
          "sell": 4.9827,
          "description": "İsveç Kronu",
          "changeRatio": 0.33,
          "flagCode": "se/tr"
        },
        "TL/SEK": {
          "buy": 0.20069440263311056,
          "sell": 0.20989442310517809,
          "description": "Türk Lirası",
          "changeRatio": -0.28,
          "flagCode": "tr/se"
        },
        "XPT/USD": {
          "buy": 65.51645,
          "sell": 69.70829,
          "description": "Platin",
          "changeRatio": 0,
          "flagCode": "xpt/us"
        },
        "USD/XPT": {
          "buy": 0.014345496066536704,
          "sell": 0.015263342259844664,
          "description": "Amerikan Doları",
          "changeRatio": 0.1,
          "flagCode": "us/xpt"
        },
        "XPD/USD": {
          "buy": 48.72686,
          "sell": 51.84448,
          "description": "Paladyum",
          "changeRatio": 0,
          "flagCode": "xpd/us"
        },
        "USD/XPD": {
          "buy": 0.019288456553137386,
          "sell": 0.02052256188886376,
          "description": "Amerikan Doları",
          "changeRatio": 0.1,
          "flagCode": "us/xpd"
        },
        "GMS/USD": {
          "buy": 2.41175,
          "sell": 2.64432,
          "description": "Gümüş (Gram)",
          "changeRatio": 0,
          "flagCode": "gms/us"
        },
        "USD/GMS": {
          "buy": 0.378169056695105,
          "sell": 0.4146366746138696,
          "description": "Amerikan Doları",
          "changeRatio": 0.21,
          "flagCode": "us/gms"
        },
        "EUR/USD": {
          "buy": 1.17732,
          "sell": 1.17968,
          "description": "Avrupa Para Birimi",
          "changeRatio": 0,
          "flagCode": "eu/us"
        },
        "USD/EUR": {
          "buy": 0.847687508476875,
          "sell": 0.8493867427717189,
          "description": "Amerikan Doları",
          "changeRatio": 0,
          "flagCode": "us/eu"
        },
        "GBP/USD": {
          "buy": 1.35185,
          "sell": 1.35455,
          "description": "İngiliz Sterlini",
          "changeRatio": 0,
          "flagCode": "uk/us"
        },
        "USD/GBP": {
          "buy": 0.7382525561994758,
          "sell": 0.7397270407219736,
          "description": "Amerikan Doları",
          "changeRatio": 0,
          "flagCode": "us/uk"
        },
        "USD/JPY": {
          "buy": 158.95589,
          "sell": 159.27412,
          "description": "Amerikan Doları",
          "changeRatio": 0,
          "flagCode": "us/jp"
        },
        "JPY/USD": {
          "buy": 0.006278483911887254,
          "sell": 0.006291053448853012,
          "description": "Japon Yeni (100)",
          "changeRatio": 0,
          "flagCode": "jp/us"
        },
        "ALT/USD": {
          "buy": 149.31878,
          "sell": 158.87242,
          "description": "Altın (Gram)",
          "changeRatio": 0,
          "flagCode": "au/us"
        },
        "USD/ALT": {
          "buy": 0.006294358706187014,
          "sell": 0.006697081237872423,
          "description": "Amerikan Doları",
          "changeRatio": 0.1,
          "flagCode": "us/au"
        },
        "EUR/GBP": {
          "buy": 0.86916,
          "sell": 0.87264,
          "description": "Avrupa Para Birimi",
          "changeRatio": 0,
          "flagCode": "eu/uk"
        },
        "GBP/EUR": {
          "buy": 1.145947928126146,
          "sell": 1.1505361498458282,
          "description": "İngiliz Sterlini",
          "changeRatio": 0,
          "flagCode": "uk/eu"
        },
        "USD/CHF": {
          "buy": 0.78222,
          "sell": 0.78378,
          "description": "Amerikan Doları",
          "changeRatio": 0,
          "flagCode": "us/ch"
        },
        "CHF/USD": {
          "buy": 1.275868228329378,
          "sell": 1.278412722763417,
          "description": "İsviçre Frangı",
          "changeRatio": 0,
          "flagCode": "ch/us"
        },
        "EUR/CHF": {
          "buy": 0.92092,
          "sell": 0.92461,
          "description": "Avrupa Para Birimi",
          "changeRatio": 0,
          "flagCode": "eu/ch"
        },
        "CHF/EUR": {
          "buy": 1.081537080498805,
          "sell": 1.0858706510880425,
          "description": "İsviçre Frangı",
          "changeRatio": 0,
          "flagCode": "ch/eu"
        },
        "USD/CAD": {
          "buy": 1.36838,
          "sell": 1.37112,
          "description": "Amerikan Doları",
          "changeRatio": 0,
          "flagCode": "us/ca"
        },
        "CAD/USD": {
          "buy": 0.7293307660890368,
          "sell": 0.7307911545038659,
          "description": "Kanada Doları",
          "changeRatio": 0,
          "flagCode": "ca/us"
        },
        "USD/DKK": {
          "buy": 6.33491,
          "sell": 6.34759,
          "description": "Amerikan Doları",
          "changeRatio": 0,
          "flagCode": "us/dk"
        },
        "DKK/USD": {
          "buy": 0.157540105772427,
          "sell": 0.15785543914593894,
          "description": "Danimarka Kronu",
          "changeRatio": 0,
          "flagCode": "dk/us"
        },
        "USD/NOK": {
          "buy": 9.35289,
          "sell": 9.37161,
          "description": "Amerikan Doları",
          "changeRatio": 0,
          "flagCode": "us/no"
        },
        "NOK/USD": {
          "buy": 0.10670525128553152,
          "sell": 0.10691882402123835,
          "description": "Norveç Kronu",
          "changeRatio": 0,
          "flagCode": "no/us"
        },
        "USD/SEK": {
          "buy": 9.17646,
          "sell": 9.19484,
          "description": "Amerikan Doları",
          "changeRatio": 0,
          "flagCode": "us/se"
        },
        "SEK/USD": {
          "buy": 0.1087566504691762,
          "sell": 0.10897448471414903,
          "description": "İsveç Kronu",
          "changeRatio": 0,
          "flagCode": "se/us"
        },
        "EUR/JPY": {
          "buy": 187.14218,
          "sell": 187.89225,
          "description": "Avrupa Para Birimi",
          "changeRatio": 0,
          "flagCode": "eu/jp"
        },
        "JPY/EUR": {
          "buy": 0.005322199292413604,
          "sell": 0.005343530784989252,
          "description": "Japon Yeni (100)",
          "changeRatio": 0,
          "flagCode": "jp/eu"
        },
        "AUD/USD": {
          "buy": 0.71548,
          "sell": 0.71692,
          "description": "Avustralya Doları",
          "changeRatio": 0,
          "flagCode": "aus/us"
        },
        "USD/AUD": {
          "buy": 1.3948557719131842,
          "sell": 1.3976631072846202,
          "description": "Amerikan Doları",
          "changeRatio": 0,
          "flagCode": "us/aus"
        }
      },
      "noChange": true
    },
    {
      "meta": {
        "id": "kuveyt",
        "rev": 1,
        "name": "Kuveyt Türk",
        "sourceUrl": "https://www.kuveytturk.com.tr/ck0d84?B83A1EF44DD940F2FEC85646BDB25EA0"
      },
      "ok": true,
      "scrapedAt": "2026-04-17T20:59:55.909Z",
      "providerUpdatedAt": null,
      "providerFingerprint": "d4fd65241f36e33394cb14d146ee29a9aa72bec2a52631ace7a5fe8eddfaaae2",
      "sourceUrl": "https://www.kuveytturk.com.tr/ck0d84?B83A1EF44DD940F2FEC85646BDB25EA0",
      "data": {
        "USD": {
          "buy": 42.76661,
          "sell": 46.68785,
          "description": "Amerikan Doları",
          "title": "USD",
          "changeRate": 3.2563862006490703,
          "changeRateNegative": false
        },
        "EUR": {
          "buy": 50.29781,
          "sell": 54.95767,
          "description": "Euro",
          "title": "EUR",
          "changeRate": 3.2414803382015682,
          "changeRateNegative": false
        },
        "ALT (gr)": {
          "buy": 6664.13555,
          "sell": 7299.61395,
          "description": "Altın",
          "title": "ALT (gr)",
          "changeRate": 5.368092781679755,
          "changeRateNegative": false
        },
        "GMS (gr)": {
          "buy": 111.7551,
          "sell": 123.08851,
          "description": "Gümüş",
          "title": "GMS (gr)",
          "changeRate": 7.312349761763525,
          "changeRateNegative": false
        },
        "PLT (gr)": {
          "buy": 2886.41047,
          "sell": 3223.28852,
          "description": "Platin",
          "title": "PLT (gr)",
          "changeRate": 4.797865808067382,
          "changeRateNegative": false
        },
        "ZCeyrek": {
          "buy": 10744.09683,
          "sell": 11768.63202,
          "description": "Çeyrek Altın (22 ayar)",
          "title": "Çeyrek",
          "changeRate": 3.9364049200826945,
          "changeRateNegative": false
        },
        "EUR/USD": {
          "buy": 1.15846,
          "sell": 1.19479,
          "description": "EUR/USD",
          "title": "EUR/USD",
          "changeRate": -1.2959349732037115,
          "changeRateNegative": true
        }
      },
      "noChange": false
    },
    {
      "meta": {
        "id": "yapi",
        "rev": 1,
        "name": "Yapı Kredi",
        "sourceUrl": "https://www.yapikredi.com.tr/_ajaxproxy/general.aspx/LoadMainCurrencies"
      },
      "ok": true,
      "scrapedAt": "2026-04-17T20:59:58.212Z",
      "providerUpdatedAt": "2026-04-17T23:57:10+03:00",
      "providerFingerprint": "31eea1acb5c373fb56a839c7e8e44f1a3fab0153a82d5afd9c42aa76eda60ffb",
      "sourceUrl": "https://www.yapikredi.com.tr/_ajaxproxy/general.aspx/LoadMainCurrencies",
      "data": {
        "EUR": {
          "buy": 51.32161,
          "sell": 53.884,
          "dailyStatus": "up",
          "change": 0.049661804,
          "previousDayBuyingPrice": 52.058876,
          "previousDaySellingPrice": 53.09451
        },
        "USD": {
          "buy": 43.5485344,
          "sell": 45.8885422,
          "dailyStatus": "up",
          "change": 0.108347833,
          "previousDayBuyingPrice": 44.20901,
          "previousDaySellingPrice": 45.1312675
        },
        "XAU": {
          "buy": 6783.09863,
          "sell": 7076.80127,
          "dailyStatus": "up",
          "change": 1.01297927,
          "previousDayBuyingPrice": 6769.74,
          "previousDaySellingPrice": 6951.16943
        }
      },
      "noChange": false
    }
  ]
}
